puzzle/__init__.py
puzzle/plugin_collection.py
puzzle/telegram.py
puzzle/tools.py
puzzle/webhook.py
puzzle_core-1.0.0.dist-info/LICENSE
puzzle_core-1.0.0.dist-info/METADATA
puzzle_core-1.0.0.dist-info/WHEEL
puzzle_core-1.0.0.dist-info/top_level.txt
puzzle_core-1.0.0.dist-info/RECORD
